etw/GUID.py
etw/__init__.py
etw/common.py
etw/etw.py
etw/evntcons.py
etw/evntprov.py
etw/evntrace.py
etw/in6addr.py
etw/tdh.py
etw/wmistr.py
pywintrace-0.2.0.data/scripts/list_providers.py
pywintrace-0.2.0.data/scripts/parse_cs.py
pywintrace-0.2.0.dist-info/LICENSE.txt
pywintrace-0.2.0.dist-info/METADATA
pywintrace-0.2.0.dist-info/WHEEL
pywintrace-0.2.0.dist-info/top_level.txt
pywintrace-0.2.0.dist-info/RECORD
