Metadata-Version: 2.1
Name: pywintrace
Version: 0.2.0
Summary: ETW Tracing
Home-page: https://github.com/fireeye/pywintrace
Author: Anthony Berglund
Author-email: anthony.berglund@fireeye.com
License: Apache
Download-URL: https://github.com/fireeye/pywintrace/archive/v0.1.1.tar.gz
Platform: Windows
Classifier: Environment :: Console
Classifier: Operating System :: Microsoft :: Windows
Classifier: License :: OSI Approved :: Apache Software License
Classifier: Programming Language :: Python :: 3
Classifier: Topic :: Software Development :: Libraries
